bk_audit/__init__.py
bk_audit/client.py
bk_audit/constants/__init__.py
bk_audit/constants/contrib.py
bk_audit/constants/log.py
bk_audit/constants/utils.py
bk_audit/contrib/__init__.py
bk_audit/contrib/bk_audit/__init__.py
bk_audit/contrib/bk_audit/apps.py
bk_audit/contrib/bk_audit/client.py
bk_audit/contrib/bk_audit/settings.py
bk_audit/contrib/django/__init__.py
bk_audit/contrib/django/formatters.py
bk_audit/contrib/django/loggers.py
bk_audit/contrib/django/resources.py
bk_audit/contrib/opentelemetry/__init__.py
bk_audit/contrib/opentelemetry/exporters.py
bk_audit/contrib/opentelemetry/processor.py
bk_audit/contrib/opentelemetry/setup.py
bk_audit/contrib/opentelemetry/utils.py
bk_audit/log/__init__.py
bk_audit/log/base.py
bk_audit/log/exporters.py
bk_audit/log/formatters.py
bk_audit/log/models.py
bk_audit/log/queue.py
bk_audit/utils/__init__.py
bk_audit/utils/decorators.py
bk_audit/utils/time_tool.py
bk_audit-1.2.2.dist-info/METADATA
bk_audit-1.2.2.dist-info/WHEEL
bk_audit-1.2.2.dist-info/top_level.txt
bk_audit-1.2.2.dist-info/RECORD
