Metadata-Version: 2.1
Name: bk-audit
Version: 1.2.2
Summary: Bk Audit SDK
Home-page: https://bk.tencent.com
Author: blueking
Author-email: blueking@tencent.com
Classifier: Programming Language :: Python :: 3.10
Classifier: Programming Language :: Python :: 3.11
Classifier: Programming Language :: Python :: 3.12
Classifier: License :: OSI Approved :: MIT License
Classifier: Operating System :: OS Independent
Requires: bk_iam
Requires-Python: >=3.10, <4
Provides-Extra: bk_resource
Requires-Dist: bk-resource >=0.4.0 ; extra == 'bk_resource'
Provides-Extra: opentelemetry
Requires-Dist: protobuf >=3.19.5 ; extra == 'opentelemetry'
Requires-Dist: opentelemetry-api >=1.20.0 ; extra == 'opentelemetry'
Requires-Dist: opentelemetry-sdk >=1.20.0 ; extra == 'opentelemetry'
Requires-Dist: opentelemetry-exporter-otlp >=1.20.0 ; extra == 'opentelemetry'
